psid_py/__init__.py
psid_py/psid_py.py
psid_py/read_sas.py
psid_py/test.py
psid_py-1.0.2.dist-info/DESCRIPTION.rst
psid_py-1.0.2.dist-info/METADATA
psid_py-1.0.2.dist-info/RECORD
psid_py-1.0.2.dist-info/WHEEL
psid_py-1.0.2.dist-info/metadata.json
psid_py-1.0.2.dist-info/top_level.txt
