Metadata-Version: 2.0
Name: psid-py
Version: 1.0.2
Summary: A tool to build PSID panels.
Home-page: https://github.com/tyler-abbot/psidPy
Author: Tyler Abbot
Author-email: tyler.abbot@sciencespo.fr
License: MIT
Keywords: statistics econometrics data
Platform: UNKNOWN
Classifier: Development Status :: 3 - Alpha
Classifier: Intended Audience :: Science/Research
Classifier: Topic :: Scientific/Engineering :: Information Analysis
Classifier: License :: OSI Approved :: MIT License
Classifier: Programming Language :: Python :: 2
Classifier: Programming Language :: Python :: 2.6
Classifier: Programming Language :: Python :: 2.7
Classifier: Programming Language :: Python :: 3
Classifier: Programming Language :: Python :: 3.2
Classifier: Programming Language :: Python :: 3.3
Classifier: Programming Language :: Python :: 3.4
Requires-Dist: beautifulsoup4
Requires-Dist: pandas
Requires-Dist: requests
